snowstorm_client/__init__.py
snowstorm_client/api_client.py
snowstorm_client/api_response.py
snowstorm_client/configuration.py
snowstorm_client/exceptions.py
snowstorm_client/py.typed
snowstorm_client/rest.py
snowstorm_client/api/__init__.py
snowstorm_client/api/admin_api.py
snowstorm_client/api/admin_permissions_api.py
snowstorm_client/api/authoring_stats_api.py
snowstorm_client/api/branching_api.py
snowstorm_client/api/classification_api.py
snowstorm_client/api/code_systems_api.py
snowstorm_client/api/concepts_api.py
snowstorm_client/api/descriptions_api.py
snowstorm_client/api/export_api.py
snowstorm_client/api/identifiers_api.py
snowstorm_client/api/import_api.py
snowstorm_client/api/mrcm_api.py
snowstorm_client/api/multi_search_api.py
snowstorm_client/api/refset_members_api.py
snowstorm_client/api/relationships_api.py
snowstorm_client/api/utility_functions_api.py
snowstorm_client/api/validation_api.py
snowstorm_client/api/version_api.py
snowstorm_client/api/web_route_api.py
snowstorm_client/models/__init__.py
snowstorm_client/models/annotation.py
snowstorm_client/models/annotation_component.py
snowstorm_client/models/api_error.py
snowstorm_client/models/async_concept_change_batch.py
snowstorm_client/models/async_refset_member_change_batch.py
snowstorm_client/models/authoring_stats_summary.py
snowstorm_client/models/axiom.py
snowstorm_client/models/axiom_component.py
snowstorm_client/models/branch.py
snowstorm_client/models/branch_merge_job.py
snowstorm_client/models/branch_pojo.py
snowstorm_client/models/branch_review.py
snowstorm_client/models/branch_review_concept_changes.py
snowstorm_client/models/branch_state.py
snowstorm_client/models/browser_description_search_result_component.py
snowstorm_client/models/build_version.py
snowstorm_client/models/classification.py
snowstorm_client/models/code_system.py
snowstorm_client/models/code_system_upgrade_job.py
snowstorm_client/models/code_system_version.py
snowstorm_client/models/coding.py
snowstorm_client-0.1.0.dist-info/METADATA
snowstorm_client-0.1.0.dist-info/WHEEL
snowstorm_client-0.1.0.dist-info/top_level.txt
snowstorm_client-0.1.0.dist-info/RECORD
