Metadata-Version: 2.4
Name: snowstorm-client
Version: 0.1.0
Summary: Add your description here
Requires-Python: >=3.9
Requires-Dist: urllib3<3.0.0,>=2.1.0
Requires-Dist: python_dateutil>=2.8.2
Requires-Dist: pydantic>=2
Requires-Dist: typing-extensions>=4.7.1
